__init__.py
gather_taxi_data/__init__.py
gather_taxi_data/gather_all_data.py
gather_taxi_data/gather_bwc_data.py
gather_taxi_data/gather_gps_data.py
tests/__init__.py
gather_taxi_data-0.1.1.dist-info/LICENSE
gather_taxi_data-0.1.1.dist-info/METADATA
gather_taxi_data-0.1.1.dist-info/WHEEL
gather_taxi_data-0.1.1.dist-info/entry_points.txt
gather_taxi_data-0.1.1.dist-info/top_level.txt
gather_taxi_data-0.1.1.dist-info/RECORD
