Metadata-Version: 2.1
Name: gather_taxi_data
Version: 0.1.1
Summary: Export data from web portals and save to database.
Home-page: https://github.com/WayneBennett666/gather-taxi-data
Author: Wayne Bennett
Author-email: wayne.bennett@live.com
Classifier: Programming Language :: Python :: 3
Classifier: License :: OSI Approved :: MIT License
Classifier: Operating System :: OS Independent
Requires-Python: >=3.11
License-File: LICENSE
Requires-Dist: taxi-data-core
Requires-Dist: selenium
Requires-Dist: pydantic
Requires-Dist: beautifulsoup4
